CONFIGURATION.rst
LICENSE
MANIFEST.in
README.rst
setup.py
conf/example.conf
conf/mattermost.example.conf
conf/rocketchat.example.conf
xmppwb/__init__.py
xmppwb/bridge.py
xmppwb/core.py
xmppwb/version.py
xmppwb/xmpp.py
xmppwb.egg-info/PKG-INFO
xmppwb.egg-info/SOURCES.txt
xmppwb.egg-info/dependency_links.txt
xmppwb.egg-info/entry_points.txt
xmppwb.egg-info/requires.txt
xmppwb.egg-info/top_level.txt