Metadata-Version: 1.1
Name: xmppwb
Version: 0.5.0
Summary: XMPP Webhook Bridge
Home-page: https://github.com/saqura/xmppwb
Author: saqura
Author-email: saqura@saqura.xyz
License: MIT
Keywords: jabber,xmpp,bridge,bot,webhook,webhooks
Platform: UNKNOWN
Classifier: Development Status :: 3 - Alpha
Classifier: Intended Audience :: Developers
Classifier: Intended Audience :: System Administrators
Classifier: Topic :: Communications :: Chat
Classifier: License :: OSI Approved :: MIT License
Classifier: Programming Language :: Python
Classifier: Programming Language :: Python :: 3 :: Only
Classifier: Programming Language :: Python :: 3.5
